freeflyer_runtime_api/AsyncData.py
freeflyer_runtime_api/CInterfaceWrapper.py
freeflyer_runtime_api/ConsoleOutputProcessingMethod.py
freeflyer_runtime_api/DiagnosticLevel.py
freeflyer_runtime_api/FFTimeSpan.py
freeflyer_runtime_api/FunctionId.py
freeflyer_runtime_api/GetFreeFlyerVersionResult.py
freeflyer_runtime_api/GetLocationResult.py
freeflyer_runtime_api/GetMissionPlanDiagnosticsResult.py
freeflyer_runtime_api/GetRuntimeApiVersionResult.py
freeflyer_runtime_api/Result.py
freeflyer_runtime_api/RuntimeApiEngine.py
freeflyer_runtime_api/RuntimeApiException.py
freeflyer_runtime_api/TimeSpanMode.py
freeflyer_runtime_api/Utilities.py
freeflyer_runtime_api/WindowedOutputMode.py
freeflyer_runtime_api/__init__.py
freeflyer_runtime_api/_version.py
freeflyer_runtime_api-3.0.0.post1.dist-info/LICENSE.pdf
freeflyer_runtime_api-3.0.0.post1.dist-info/METADATA
freeflyer_runtime_api-3.0.0.post1.dist-info/WHEEL
freeflyer_runtime_api-3.0.0.post1.dist-info/top_level.txt
freeflyer_runtime_api-3.0.0.post1.dist-info/RECORD
