Metadata-Version: 2.1
Name: freeflyer-runtime-api
Version: 3.0.0.post1
Summary: Python interface to the FreeFlyer® Runtime API
Home-page: https://ai-solutions.com/freeflyer/
Author: a.i. solutions, Inc.
Author-email: techsupport@ai-solutions.com
License: UNKNOWN
Platform: UNKNOWN
Classifier: Development Status :: 6 - Mature
Classifier: Intended Audience :: Science/Research
Classifier: License :: Other/Proprietary License
Classifier: Operating System :: OS Independent
Classifier: Programming Language :: Python :: 2.7
Classifier: Programming Language :: Python :: 3
Classifier: Topic :: Scientific/Engineering
